README
setup.py
./poly2tri/common/shapes.cc
./poly2tri/sweep/advancing_front.cc
./poly2tri/sweep/cdt.cc
./poly2tri/sweep/sweep.cc
./poly2tri/sweep/sweep_context.cc
poly2tri.egg-info/PKG-INFO
poly2tri.egg-info/SOURCES.txt
poly2tri.egg-info/dependency_links.txt
poly2tri.egg-info/requires.txt
poly2tri.egg-info/top_level.txt
poly2tri/common/shapes.cc
poly2tri/sweep/advancing_front.cc
poly2tri/sweep/cdt.cc
poly2tri/sweep/sweep.cc
poly2tri/sweep/sweep_context.cc
src/cdt.pxd
src/cdt.pxi
src/p2t.cpp
src/p2t.pxd
src/p2t.pyx
src/shapes.pxd
src/shapes.pxi