Metadata-Version: 1.0
Name: poly2tri
Version: 0.3.2
Summary: A 2D constrained Delaunay triangulation library
Home-page: http://code.google.com/p/poly2tri/
Author: Mason Green
Author-email: UNKNOWN
License: UNKNOWN
Platform: UNKNOWN
